{
  "total_anomalies": 39,
  "total_impact": -63000.0,
  "insights": [
    {
      "bucket_id": 1,
      "bucket_description": "Inconsistent variations in outstanding balances",
      "anomaly_count": 17,
      "sample_companies": [
        "Doyle Ltd",
        "Galloway-Wyatt",
        "Flowers, Martin and Kelly"
      ],
      "root_cause": "The variations may be due to inconsistent accounting practices or errors in data entry.",
      "recommendation": "Conduct a detailed review of accounting practices and data entry processes."
    },
    {
      "bucket_id": 11,
      "bucket_description": "No clear pattern, but deviation exceeds threshold",
      "anomaly_count": 7,
      "sample_companies": [
        "Abbott-Munoz",
        "Martin, Rose and Obrien",
        "Brown, Valdez and Lucas"
      ],
      "root_cause": "Deviations may be caused by unusual transactions or external factors not accounted for.",
      "recommendation": "Investigate recent transactions and external factors for any unusual activities."
    },
    {
      "bucket_id": 2,
      "bucket_description": "Consistent increase or decrease in outstanding balances",
      "anomaly_count": 6,
      "sample_companies": [
        "Mcclain, Miller and Henderson",
        "James Group",
        "Williams PLC"
      ],
      "root_cause": "This could be due to changes in business operations or policy adjustments.",
      "recommendation": "Review business operations and policies to identify potential causes."
    },
    {
      "bucket_id": 8,
      "bucket_description": "Reversal or correction entry detected",
      "anomaly_count": 3,
      "sample_companies": [
        "Guzman, Hoffman and Baldwin",
        "Woods, Calhoun and Schmidt",
        "Donovan-Harris"
      ],
      "root_cause": "Reversals or corrections may have been made to rectify previous errors.",
      "recommendation": "Verify the accuracy of reversal or correction entries and ensure they are justified."
    },
    {
      "bucket_id": 4,
      "bucket_description": "Outstanding balances are not in line with previous months",
      "anomaly_count": 3,
      "sample_companies": [
        "Snyder, Campos and Callahan",
        "Harris, Collins and Carney",
        "Suarez LLC"
      ],
      "root_cause": "Discrepancies could be due to seasonal variations or errors in previous records.",
      "recommendation": "Analyze historical data for seasonal trends or errors in past records."
    },
    {
      "bucket_id": 5,
      "bucket_description": "Gradual deviation beyond threshold over multiple periods",
      "anomaly_count": 2,
      "sample_companies": [
        "Stanley, Tucker and Lee",
        "Hensley, Powell and David"
      ],
      "root_cause": "Gradual deviations may indicate underlying systemic issues.",
      "recommendation": "Conduct a root cause analysis to identify systemic issues affecting balances."
    },
    {
      "bucket_id": 7,
      "bucket_description": "High volatility in account balances over time",
      "anomaly_count": 1,
      "sample_companies": [
        "Turner, Riggs and Roman"
      ],
      "root_cause": "High volatility may be due to market fluctuations or inconsistent financial practices.",
      "recommendation": "Implement measures to stabilize financial practices and mitigate market impacts."
    }
  ]
}